socrates_cli/__init__.py
socrates_cli/cli.py
socrates_ai_cli-1.3.3.dist-info/METADATA
socrates_ai_cli-1.3.3.dist-info/WHEEL
socrates_ai_cli-1.3.3.dist-info/entry_points.txt
socrates_ai_cli-1.3.3.dist-info/top_level.txt
socrates_ai_cli-1.3.3.dist-info/RECORD
