Metadata-Version: 2.4
Name: socrates-ai-cli
Version: 1.3.3
Summary: Command-line interface for Socrates AI tutoring system with GitHub-ready project generation, export, and publishing capabilities
Author: Socrates AI Contributors
License: MIT
Project-URL: Homepage, https://github.com/Nireus79/Socrates
Project-URL: Repository, https://github.com/Nireus79/Socrates
Project-URL: Bug Tracker, https://github.com/Nireus79/Socrates/issues
Project-URL: Source Code, https://github.com/Nireus79/Socrates/tree/main/socrates-cli
Keywords: cli,command-line,socrates,ai,tutoring,education,github,export,git,ci-cd
Classifier: Development Status :: 5 - Production/Stable
Classifier: Intended Audience :: Developers
Classifier: License :: OSI Approved :: MIT License
Classifier: Programming Language :: Python :: 3
Classifier: Programming Language :: Python :: 3.8
Classifier: Programming Language :: Python :: 3.9
Classifier: Programming Language :: Python :: 3.10
Classifier: Programming Language :: Python :: 3.11
Classifier: Programming Language :: Python :: 3.12
Classifier: Environment :: Console
Classifier: Topic :: Education
Classifier: Topic :: Software Development :: Libraries :: Python Modules
Requires-Python: >=3.8
Requires-Dist: socrates-ai>=1.3.0
Requires-Dist: colorama>=0.4.6
Requires-Dist: click>=8.0.0
Provides-Extra: dev
Requires-Dist: pytest>=7.0; extra == "dev"
Requires-Dist: pytest-cov>=4.0; extra == "dev"
Requires-Dist: black>=23.0; extra == "dev"
Requires-Dist: ruff>=0.1.0; extra == "dev"
